grithopper/GritHopper.py
grithopper/__init__.py
grithopper-0.0.4.dist-info/LICENSE.txt
grithopper-0.0.4.dist-info/METADATA
grithopper-0.0.4.dist-info/NOTICE.txt
grithopper-0.0.4.dist-info/WHEEL
grithopper-0.0.4.dist-info/top_level.txt
grithopper-0.0.4.dist-info/RECORD
