Metadata-Version: 2.2
Name: grithopper
Version: 0.0.4
Summary: GritHopper: Decomposition-Free Multi-Hop Dense Retrieval
Download-URL: https://github.com/UKPLab/GritHopper/
Author: Justus-Jonas Erker
Author-email: justus-jonas.erker@tu-darmstadt.de
License: Apache License 2.0
Keywords: PyTorch NLP deep learning Multi-Hop Dense Retrieval Fact-Checking Question Answering
Classifier: Development Status :: 1 - Planning
Classifier: License :: OSI Approved :: Apache Software License
Classifier: Programming Language :: Python :: 3.9
Classifier: Topic :: Scientific/Engineering :: Artificial Intelligence
Classifier: Intended Audience :: Science/Research
Requires-Python: >=3.9.19
License-File: LICENSE.txt
License-File: NOTICE.txt
Requires-Dist: gritlm==1.0.2
Dynamic: author
Dynamic: author-email
Dynamic: classifier
Dynamic: description
Dynamic: description-content-type
Dynamic: download-url
Dynamic: keywords
Dynamic: license
Dynamic: requires-dist
Dynamic: requires-python
Dynamic: summary
